CHANGES.rst
LICENSE
MANIFEST.in
README.md
setup.py
djorm_ext_pgtrgm.egg-info/PKG-INFO
djorm_ext_pgtrgm.egg-info/SOURCES.txt
djorm_ext_pgtrgm.egg-info/dependency_links.txt
djorm_ext_pgtrgm.egg-info/not-zip-safe
djorm_ext_pgtrgm.egg-info/top_level.txt
djorm_pgtrgm/__init__.py