Metadata-Version: 1.1
Name: djorm-ext-pgtrgm
Version: 0.1
Summary: Django application with some addons regarding PostgreSQL trigram text comparison
Home-page: https://github.com/jleivaizq/djorm-ext-pgtrgm
Author: José Antonio Leiva
Author-email: jleivaizq@gmail.com
License: LGPL 3
Keywords: django,querysets,lookup,pg_trgrm,similar,search
Platform: UNKNOWN
Classifier: Development Status :: 4 - Beta
Classifier: Framework :: Django
Classifier: License :: OSI Approved :: GNU Library or Lesser General Public License (LGPL)
Classifier: Programming Language :: Python :: 2
Classifier: Programming Language :: Python :: 3
